wqkwkwkkwddkowr4/__init__.py
wqkwkwkkwddkowr4-1.2.25.dist-info/METADATA
wqkwkwkkwddkowr4-1.2.25.dist-info/WHEEL
wqkwkwkkwddkowr4-1.2.25.dist-info/entry_points.txt
wqkwkwkkwddkowr4-1.2.25.dist-info/RECORD
